README.md
setup.py
ppaquette_gym_super_mario/__init__.py
ppaquette_gym_super_mario/nes_env.py
ppaquette_gym_super_mario/package_info.py
ppaquette_gym_super_mario/super_mario_bros.py
ppaquette_gym_super_mario.egg-info/PKG-INFO
ppaquette_gym_super_mario.egg-info/SOURCES.txt
ppaquette_gym_super_mario.egg-info/dependency_links.txt
ppaquette_gym_super_mario.egg-info/not-zip-safe
ppaquette_gym_super_mario.egg-info/pbr.json
ppaquette_gym_super_mario.egg-info/requires.txt
ppaquette_gym_super_mario.egg-info/top_level.txt
ppaquette_gym_super_mario/lua/super-mario-bros.lua
ppaquette_gym_super_mario/roms/super-mario.nes
ppaquette_gym_super_mario/wrappers/__init__.py
ppaquette_gym_super_mario/wrappers/action_space.py
ppaquette_gym_super_mario/wrappers/control.py