Metadata-Version: 1.0
Name: ppaquette-gym-super-mario
Version: 0.0.8
Summary: Gym User Env - 32 levels of Super Mario Bros
Home-page: https://github.com/ppaquette/gym_super_mario
Author: Philip Paquette
Author-email: pcpaquette@gmail.com
License: MIT License
Platform: UNKNOWN
